galleristazurestorage/__init__.py
galleristazurestorage/aio.py
gallerist_azurestorage-0.0.5.dist-info/LICENSE
gallerist_azurestorage-0.0.5.dist-info/METADATA
gallerist_azurestorage-0.0.5.dist-info/WHEEL
gallerist_azurestorage-0.0.5.dist-info/top_level.txt
gallerist_azurestorage-0.0.5.dist-info/RECORD
