Metadata-Version: 2.1
Name: gallerist-azurestorage
Version: 0.0.5
Summary: Azure Storage file store for Gallerist
Home-page: https://github.com/Neoteroi/Gallerist-AzureStorage
Author: RobertoPrevato
Author-email: roberto.prevato@gmail.com
License: MIT
Keywords: pictures images web azure storage
Platform: UNKNOWN
Classifier: Development Status :: 5 - Production/Stable
Classifier: License :: OSI Approved :: MIT License
Classifier: Programming Language :: Python :: 3
Classifier: Programming Language :: Python :: 3.6
Classifier: Programming Language :: Python :: 3.7
Classifier: Programming Language :: Python :: 3.8
Classifier: Programming Language :: Python :: 3.9
Classifier: Operating System :: OS Independent
License-File: LICENSE
Requires-Dist: gallerist (>=0.0.6)
Requires-Dist: azure-storage-blob (==12.9.0)
